{
    "references": [
        {
            "bibentry": "Babbie, E. (2007). The practice of social research (11th ed.). Belmont, CA: Wadsworth.",
            "process_entry": "True",
            "xmlid": "CIT0001"
        },
        {
            "bibentry": "Batisai, K. (2013). Body politics: An illumination of the landscape of sexuality and nationhood? Re-seeing Zimbabwe through elderly women’s representations of their sexual and gendered lives (PhD thesis). University of Cape Town, Cape Town.",
            "process_entry": "True",
            "xmlid": "CIT0002"
        },
        {
            "bibentry": "Batisai, K. (2016). Towards an integrated approach to health and medicine in Africa. SAHARA-J: Journal of Social Aspects of HIV/AIDS, 13(1), 113–122. doi: DOI: 10.1080/17290376.2016.1220323 PMID: 27538792",
            "process_entry": "True",
            "doi": "10.1080/17290376.2016.1220323",
            "pmid": "27538792",
            "pmcid": "PMC5642441",
            "xmlid": "CIT0003"
        },
        {
            "bibentry": "Bene, M, &, Darkoh, M. B. K. (2014). The constraints of antiretroviral uptake in rural areas: The case of Thamaga and surrounding villages, Botswana. SAHARA-J: Journal of Social Aspects of HIV/AIDS, 11(1), 167–177. doi: 10. 1080/17290376.2014.972057 PMID: 25365702",
            "process_entry": "True",
            "doi": "10.1080/17290376.2014.972057",
            "pmid": "25365702",
            "pmcid": "PMC4272138",
            "xmlid": "CIT0004"
        },
        {
            "bibentry": "Bhandari, H, &, Yasunobu, K. (2009). What is social capital? A comprehensive review of the concept. Asian Journal of Social Science, 37(3), 480–510.",
            "process_entry": "True",
            "xmlid": "CIT0005"
        },
        {
            "bibentry": "Braun, V, &, Clarke, V. (2006). Using thematic analysis in psychology. Qualitative Research in Psychology, 3(2), 77–101.",
            "process_entry": "True",
            "xmlid": "CIT0006"
        },
        {
            "bibentry": "Broom, A, &, O’Brien, S. (2011). The rise and fall of HIV prevalence in Zimbabwe: The social, political and economic context. African Journal of AIDS Research, 10(3), 281–290. doi: DOI: 10.2989/16085906.2011.626303 PMID: 25859797",
            "process_entry": "True",
            "doi": "10.2989/16085906.2011.626303",
            "pmid": "25859797",
            "xmlid": "CIT0007"
        },
        {
            "bibentry": "Campbell, A. (2009). A day in the life of Ruvheneko at St Theresa’s Mission Hospital in Rural Zimbabwe. Retrieved from http://www.pactworld.org.cs/a",
            "process_entry": "True",
            "url": "http://www.pactworld.org.cs/a",
            "xmlid": "CIT0008"
        },
        {
            "bibentry": "Centre for Disease Control (CDC) (2003). Zimbabwe opens first AIDS testing centre in rural setting’. The Body/The Complete HIV/AIDS Response. Retrieved from http://www.projectinform.org/HIVhealth/",
            "process_entry": "True",
            "url": "http://www.projectinform.org/HIVhealth/",
            "xmlid": "CIT0009"
        },
        {
            "bibentry": "Chambers, R. (1994). Participatory rural appraisal (PRA): Analysis of experience. World Development, 22(9), 1253–1268.",
            "process_entry": "True",
            "xmlid": "CIT0010"
        },
        {
            "bibentry": "Clifford, P. (2004). Theology and the HIV/AIDS epidemic. London: Christian Aid.",
            "process_entry": "True",
            "xmlid": "CIT0011"
        },
        {
            "bibentry": "Coleman, J. S. (1990). Foundations of social theory. Cambridge, MA: Harvard University Press.",
            "process_entry": "True",
            "xmlid": "CIT0012"
        },
        {
            "bibentry": "Creswell, J. W. (2007). Research design: Qualitative and quantitative approaches. London: SAGE Publication.",
            "process_entry": "True",
            "xmlid": "CIT0013"
        },
        {
            "bibentry": "Duffy, L. (2005). Culture and context of HIV prevention in rural Zimbabwe: The influence of gender Inequality. Journal of Transcultural Nursing, 16, 23–31. PMID: 15608096",
            "process_entry": "True",
            "doi": "10.1177/1043659604270962",
            "pmid": "15608096",
            "xmlid": "CIT0014"
        },
        {
            "bibentry": "Duri, K,, Stray-Pedersen, B, &, Muller, F. (2013). HIV/AIDS: The Zimbabwean situation and trends. American Journal of Clinical Medicine Research, 1(1), 15–22.",
            "process_entry": "True",
            "xmlid": "CIT0015"
        },
        {
            "bibentry": "Emmett, T. (2000). Beyond community participation? Alternative routes to civil engagement and development in South Africa. Development Southern Africa, 17(4), 501–518.",
            "process_entry": "True",
            "xmlid": "CIT0016"
        },
        {
            "bibentry": "Evans, P. (1996). Government action, social capital and development: Reviewing the evidence on synergy. World, 24(6), 111–1132.",
            "process_entry": "True",
            "xmlid": "CIT0017"
        },
        {
            "bibentry": "Familusi, O. O. (2012). African culture and the status of women: The Yoruba example. The Journal of Pan African Studies, 5(1), 299–313.",
            "process_entry": "True",
            "xmlid": "CIT0018"
        },
        {
            "bibentry": "Fine, B. (2001). The social capital of the work bank. In, Fine, B,, Lapasvistas, C, &, Pincus, J. (Eds.). Development policy in the twenty century: Beyond the post-Washington consensus (pp. 136–154). London: Routledge.",
            "process_entry": "True",
            "xmlid": "CIT0019"
        },
        {
            "bibentry": "Goldstein, S,, Usdin, S,, Scheepers, E, &, Japheth, G. (2005). Communicating HIV and AIDS, what works? A report on the impact evaluation of Soul city’s fourth series. Journal of Health Communication, 10(5), 465–483. PMID: 16199389",
            "process_entry": "True",
            "doi": "10.1080/10810730591009853",
            "pmid": "16199389",
            "xmlid": "CIT0020"
        },
        {
            "bibentry": "Haines, J. (2008). Development studies. Cambridge: Polity Press.",
            "process_entry": "True",
            "xmlid": "CIT0021"
        },
        {
            "bibentry": "Hawe, P, &, Shiell, A. (2000). Social capital and health promotion: A review. Social Science & Medicine, 51, 871–885. PMID: 10972431",
            "process_entry": "True",
            "doi": "10.1016/s0277-9536(00)00067-8",
            "pmid": "10972431",
            "xmlid": "CIT0022"
        },
        {
            "bibentry": "Hayes, N. (1997). Theory-led thematic analysis: Social identification in small companies. In, Hayes, N. (Ed.). Doing qualitative analysis in psychology (pp. 93–114). Hove, UK: Psychology Press.",
            "process_entry": "True",
            "xmlid": "CIT0023"
        },
        {
            "bibentry": "Heal The Sick (2003). Mission Doctors Association news letter. Retrieved from http://missiondoctors.org/wp-content/uploads/2010/10/newsletter_2003.pdf",
            "process_entry": "True",
            "url": "http://missiondoctors.org/wp-content/uploads/2010/10/newsletter_2003.pdf",
            "xmlid": "CIT0024"
        },
        {
            "bibentry": "Hennink, M,, Hutter, I, &, Bailey, A. (2011). Qualitative research methods. London: Sage Publications.",
            "process_entry": "True",
            "xmlid": "CIT0025"
        },
        {
            "bibentry": "Jackson, H, &, Anderson, S. (2001). Home care for people with AIDS. In, Lamptey, P. R, &, Gayle, H. D. (Eds.). HIV prevention and care in resource-constrained settings: A hand book for the Design and management of programs (pp. 579–601). Virginia: Family Health International.",
            "process_entry": "True",
            "xmlid": "CIT0026"
        },
        {
            "bibentry": "Kaseke, E, &, Dhemba, J. (2007). Community mobilisation, volunteerism and fight against HIV and AIDS in Zimbabwe. In, Patel, L. &, Mupedziswa, R. (Eds.). Research partnerships build the service field in Africa: Special issue on civic service in the Southern African development community (pp. 85–89). Johannesburg: The Social Work Practitioner-Researcher, University of Johannesburg.",
            "process_entry": "True",
            "xmlid": "CIT0027"
        },
        {
            "bibentry": "Kautzky, K, &, Tollman, S. M. (2008). A perspective on primary health care in South Africa. In, Barron, P. &, Roma-Reardon, J. (Eds.). South African health review (pp. 17–30). Durban: Health Systems Trust.",
            "process_entry": "True",
            "xmlid": "CIT0028"
        },
        {
            "bibentry": "Leff, B. (2017). Why I believe in hospital at home. Retrieved from https://catalyst.nejm.org/why-i-believe-in-hospital-at-home/",
            "process_entry": "True",
            "url": "https://catalyst.nejm.org/why-i-believe-in-hospital-at-home/",
            "xmlid": "CIT0029"
        },
        {
            "bibentry": "Madzingira, N,, Muhwava, W. B, &, Mapfumo, O. M. (2007). Sida funded HIV and AIDS projects in Zimbabwe. Retrieved from http://www.sida.se/publications",
            "process_entry": "True",
            "url": "http://www.sida.se/publications",
            "xmlid": "CIT0030"
        },
        {
            "bibentry": "Mapenzauswa, S. (2004, June 15). Zimbabwe holds first national meeting on AIDS Crisis. Reuters NewsMedia. Retrieved from http://www.sciepub.com/reference/744",
            "process_entry": "True",
            "url": "http://www.sciepub.com/reference/744",
            "xmlid": "CIT0031"
        },
        {
            "bibentry": "Marinda, E,, Humphrey, J. H,, Iliff, P. J,, Mutasa, K,, Nathoo, K. J,, Piwoz, E. G, …, Zvandasara, P. (2007). Child mortality according to maternal and infant HIV status in Zimbabwe. The Pediatric Infectious Disease Journal, 26(6), 519–526. doi: DOI: 10.1097/01.inf.0000264527.69954.4c PMID: 17529870",
            "process_entry": "True",
            "doi": "10.1097/01.inf.0000264527.69954.4c",
            "pmid": "17529870",
            "xmlid": "CIT0032"
        },
        {
            "bibentry": "Mbiti, J. S. (1969). African religions and philosophy. Nairobi: E.A.E.P.",
            "process_entry": "True",
            "xmlid": "CIT0033"
        },
        {
            "bibentry": "McMillan, J. M, &, Schumacher, S. (2006). Research in education: Evidence-based inquiry (6th ed.). Boston: Pearson Education.",
            "process_entry": "True",
            "xmlid": "CIT0034"
        },
        {
            "bibentry": "Mosse, D. (2006). Collective action, common property and social capital in South India: An anthropological commentary. Economic Development and Cultural Change, 54(3), 695–724.",
            "process_entry": "True",
            "xmlid": "CIT0035"
        },
        {
            "bibentry": "MSF Report (2009). Beyond Cholera: Zimbabwe’s worsening crisis. Médecins SansFrontieres/Doctors without Borders (MSF).",
            "process_entry": "True",
            "xmlid": "CIT0036"
        },
        {
            "bibentry": "Munshi, S, &, Bezuidenhout, J. (2017). System failures in mental health. Retrieved from https://www.wits.ac.za/news/latest-news/in-their-own-words/2017/2017-02/system-failures-in-mental-health.html",
            "process_entry": "True",
            "url": "https://www.wits.ac.za/news/latest-news/in-their-own-words/2017/2017-02/system-failures-in-mental-health-.html",
            "xmlid": "CIT0037"
        },
        {
            "bibentry": "National AIDS Council of Zimbabwe (NAC) (1999). Act 16/1999, 22/2001 (s.4). CHAPTER 15:14. Retrieved from http://www.hivaidszimbabwe.org/services/resources-in-zimbabwe/name/national-aids-council-of-zimbabwe/",
            "process_entry": "True",
            "url": "http://www.hivaidszimbabwe.org/services/resources-in-zimbabwe/name/national-aids-council-of-zimbabwe/",
            "xmlid": "CIT0038"
        },
        {
            "bibentry": "Navarro, V. (2002). A critique of social capital. International Journal of Health Sciences, 32(3), 423–432.",
            "process_entry": "True",
            "xmlid": "CIT0039"
        },
        {
            "bibentry": "Naylor, M, &, Keating, S. A. (2008). Transnational care: Moving patients from one care setting to another. American Journal of Nursing, 108(9), 58–63.",
            "process_entry": "True",
            "xmlid": "CIT0040"
        },
        {
            "bibentry": "O’Brien, S, &, Broom, A. (2014). HIV in (and out of) the clinic: Biomedicine, traditional medicine and spiritual healing in Harare. SAHARA-J: Journal of Social Aspects of HIV/AIDS, 11(1), 94–104. doi: DOI: 10.1080/17290376.2014.938102 PMID: 25017937",
            "process_entry": "True",
            "doi": "10.1080/17290376.2014.938102",
            "pmid": "25017937",
            "pmcid": "PMC4272101",
            "xmlid": "CIT0041"
        },
        {
            "bibentry": "Physicians for Human Rights (PHR) (2009). Health in ruins: A man-made disaster in Zimbabwe. Retrieved from http://physiciansforhumanrights.org/library/report-2009-01-13.html",
            "process_entry": "True",
            "url": "http://physiciansforhumanrights.org/library/report-2009-01-13.html",
            "xmlid": "CIT0042"
        },
        {
            "bibentry": "Pierce, R. (2008). Analyzing qualitative information: Classifying, coding and interpreting information. In, Pierce, R. (Ed.). Research methods in politics (pp. 171–197). London: SAGE Publications.",
            "process_entry": "True",
            "xmlid": "CIT0043"
        },
        {
            "bibentry": "Power, R. (1998). The role of qualitative research in HIV and AIDS. AIDS, 12(7), 687–695. PMID: 9619799",
            "process_entry": "True",
            "doi": "10.1097/00002030-199807000-00004",
            "pmid": "9619799",
            "xmlid": "CIT0044"
        },
        {
            "bibentry": "Price-Smith, A. (2007). Vicious-Cycle-HIV/AIDS, State capacity and National Security. Lessons from Zimbabwe, 1990-2005, Global Health Governance, 1(1), 1–22.",
            "process_entry": "True",
            "xmlid": "CIT0045"
        },
        {
            "bibentry": "Putnam, R. D. (1993). The prosperous community. Social capital and public life. The American Prospect, 4(13), 35–42.",
            "process_entry": "True",
            "xmlid": "CIT0046"
        },
        {
            "bibentry": "Putnam, R. D. (1995). Bowling alone: America’s declining social capital. Journal of Democracy, 6(1), 65–78.",
            "process_entry": "True",
            "xmlid": "CIT0047"
        },
        {
            "bibentry": "Rembe, S. (2006). An assessment of the policies and programmes of Zimbabwe in addressing the HIV and AIDS epidemic in the education sector. Education Research Reviews, 1(7), 23–255.",
            "process_entry": "True",
            "xmlid": "CIT0048"
        },
        {
            "bibentry": "Rodriguez-García, R,, Wilson, D,, York, N,, Low, C,, N'Jie, N, &, Bonne, R. (2013). Evaluation of the community response to HIV and AIDS: Learning from a portfolio approach. AIDS Care, 1(25), 7–19.",
            "process_entry": "True",
            "xmlid": "CIT0049"
        },
        {
            "bibentry": "Ruvheneko Programme Report on Key Programme Achievements for the period (2003–2009). Zimbabwe.",
            "process_entry": "True",
            "xmlid": "CIT0050"
        },
        {
            "bibentry": "Schwobel, C. (2006). Recovering human dignity. In, Soulen, R. K. &, Woodhead, L. (Eds.). God and Human Dignity (pp. 44–58). Grand Rapids: Wm. B. Eerdmans Publishing Company.",
            "process_entry": "True",
            "xmlid": "CIT0051"
        },
        {
            "bibentry": "Seamark, C. J, &, Lings, P. (2004). Positive experiences of teen motherhood: A qualitative study. British Journal of General Practice, 54(1), 813–818. PMID: 15527606",
            "process_entry": "True",
            "pmid": "15527606",
            "pmcid": "PMC1324913",
            "xmlid": "CIT0052"
        },
        {
            "bibentry": "St Theresa’s Hospital Annual Report (1999). Zimbabwe.",
            "process_entry": "True",
            "xmlid": "CIT0053"
        },
        {
            "bibentry": "St Theresa’s Hospital Annual Report (2001). Zimbabwe.",
            "process_entry": "True",
            "xmlid": "CIT0054"
        },
        {
            "bibentry": "St Theresa’s Hospital Annual Report (2009). Zimbabwe.",
            "process_entry": "True",
            "xmlid": "CIT0055"
        },
        {
            "bibentry": "Swanepoel, H, &, De Beer, F. (2006). Community Development: Breaking the cycle of poverty. Community Development: Breaking the cycle of poverty: South Africa, Juta mad Co Ltd.",
            "process_entry": "True",
            "xmlid": "CIT0056"
        },
        {
            "bibentry": "The Herald (2003). Zimbabwe: Chirumhanzu District Gets AIDS Testing Centre, 9 June. http://www.herald.co.zw",
            "process_entry": "True",
            "url": "http://www.herald.co.zw",
            "xmlid": "CIT0057"
        },
        {
            "bibentry": "Thomas, J, &, Harden, A. (2008). Methods for the thematic synthesis of qualitative research in systematic reviews. BMC Medical Research Methodology, 8(45), 1–10. PMID: 18215293",
            "process_entry": "True",
            "doi": "10.1186/1471-2288-8-1",
            "pmid": "18215293",
            "pmcid": "PMC2244639",
            "xmlid": "CIT0058"
        },
        {
            "bibentry": "United Nations Children’s Education Fund (UNICEF) (2003). Africa’s orphaned generations. New York: United Nations Children’s Fund Retrieved from http://www.unicef.org/sowc06/pdfs/africas_orphans.pdf",
            "process_entry": "True",
            "url": "http://www.unicef.org/sowc06/pdfs/africas_orphans.pdf",
            "xmlid": "CIT0059"
        },
        {
            "bibentry": "United Nations Programme on AIDS (UNAIDS) (2014). Zimbabwe AIDS Response Progress Report 2014. Retrieved from http://www.unaids.org/sites/default/files/country/documents/ZWE_narrative_report_2014.pdf",
            "process_entry": "True",
            "url": "http://www.unaids.org/sites/default/files/country/documents/ZWE_narrative_report_2014.pdf",
            "xmlid": "CIT0060"
        },
        {
            "bibentry": "World Health Organisation (WHO) (2005). Zimbabwe: Summary country profile for HIV/AIDS treatment scale –UP. Retrieved from http://www.who.int/hiv/HIVCP_ZWE.pdf",
            "process_entry": "True",
            "url": "http://www.who.int/hiv/HIVCP_ZWE.pdf",
            "xmlid": "CIT0061"
        },
        {
            "bibentry": "World Health Organisation (WHO) (2006). Antiretroviral drugs for treating pregnant women and preventing HIV infection in infants: Towards universal access. Geneva: WHO.",
            "process_entry": "True",
            "xmlid": "CIT0062"
        },
        {
            "bibentry": "Yin, R. K. (2003). Case study research: Design and methods (3rd ed.). Thousand Oaks, CA: Sage.",
            "process_entry": "True",
            "xmlid": "CIT0063"
        },
        {
            "bibentry": "Yin, R. K. (2013). Validity and generalization in future case study evaluations. Evaluation, 19(3), 321–332.",
            "process_entry": "True",
            "xmlid": "CIT0064"
        },
        {
            "bibentry": "Zimbabwe National HIV and AIDS Strategic Plan (ZNSP) (2006–2010). Harare, National AIDS Council.",
            "process_entry": "True",
            "xmlid": "CIT0065"
        }
    ],
    "localid": "MED-30991895",
    "doi": "10.1080/17290376.2019.1605537",
    "pmid": "10.1080/17290376.2019.1605537",
    "pmcid": "30991895",
    "curator": "BEE EuropeanPubMedCentralProcessor",
    "source_provider": "Europe PubMed Central",
    "source": "https://www.ebi.ac.uk/europepmc/webservices/rest/30991895/fullTextXML",
    "reference_pointers": [
        [
            {
                "n_rp": 0,
                "xref_id": "CIT0007",
                "rp_string": "2011",
                "rp_xpath": "/article/body/sec[1]/p[1]/xref[1]",
                "context_xpath": "substring(string(/article/body/sec[1]/p[1]),1,309)",
                "containers_title": [
                    "Introduction and background"
                ],
                "pl_string": "(Broom & O’Brien,2011; Mapenzauswa, 2004; Rembe, 2006; United Nations Programme on HIV and AIDS [UNAIDS], 2014; Zimbabwe National HIV and AIDS Strategic Plan (ZNASP)",
                "pl_xpath": "substring(string(/article/body/sec[1]/p[1]),131,165)"
            },
            {
                "n_rp": 1,
                "xref_id": "CIT0031",
                "rp_string": "2004",
                "rp_xpath": "/article/body/sec[1]/p[1]/xref[2]",
                "context_xpath": "substring(string(/article/body/sec[1]/p[1]),1,309)",
                "containers_title": [
                    "Introduction and background"
                ],
                "pl_string": "(Broom & O’Brien, 2011; Mapenzauswa,2004; Rembe, 2006; United Nations Programme on HIV and AIDS [UNAIDS], 2014; Zimbabwe National HIV and AIDS Strategic Plan (ZNASP)",
                "pl_xpath": "substring(string(/article/body/sec[1]/p[1]),131,165)"
            },
            {
                "n_rp": 2,
                "xref_id": "CIT0048",
                "rp_string": "2006",
                "rp_xpath": "/article/body/sec[1]/p[1]/xref[3]",
                "context_xpath": "substring(string(/article/body/sec[1]/p[1]),1,309)",
                "containers_title": [
                    "Introduction and background"
                ],
                "pl_string": "(Broom & O’Brien, 2011; Mapenzauswa, 2004; Rembe,2006; United Nations Programme on HIV and AIDS [UNAIDS], 2014; Zimbabwe National HIV and AIDS Strategic Plan (ZNASP)",
                "pl_xpath": "substring(string(/article/body/sec[1]/p[1]),131,165)"
            },
            {
                "n_rp": 3,
                "xref_id": "CIT0060",
                "rp_string": "2014",
                "rp_xpath": "/article/body/sec[1]/p[1]/xref[4]",
                "context_xpath": "substring(string(/article/body/sec[1]/p[1]),1,309)",
                "containers_title": [
                    "Introduction and background"
                ],
                "pl_string": "(Broom & O’Brien, 2011; Mapenzauswa, 2004; Rembe, 2006; United Nations Programme on HIV and AIDS [UNAIDS],2014; Zimbabwe National HIV and AIDS Strategic Plan (ZNASP)",
                "pl_xpath": "substring(string(/article/body/sec[1]/p[1]),131,165)"
            },
            {
                "n_rp": 5,
                "xref_id": "CIT0065",
                "rp_string": "2006–2010",
                "pl_string": "(ZNASP),2006–2010)",
                "rp_xpath": "/article/body/sec[1]/p[1]/xref[5]",
                "pl_xpath": "substring(string(/article/body/sec[1]/p[1]),290,18)",
                "context_xpath": "substring(string(/article/body/sec[1]/p[1]),1,309)",
                "containers_title": [
                    "Introduction and background"
                ]
            }
        ],
        [
            {
                "n_rp": 5,
                "xref_id": "CIT0065",
                "rp_string": "2006–2010",
                "pl_string": "(ZNASP),2006–2010)",
                "rp_xpath": "/article/body/sec[1]/p[1]/xref[5]",
                "pl_xpath": "substring(string(/article/body/sec[1]/p[1]),290,18)",
                "context_xpath": "substring(string(/article/body/sec[1]/p[1]),1,309)",
                "containers_title": [
                    "Introduction and background"
                ]
            },
            {
                "n_rp": 6,
                "xref_id": "",
                "pl_string": "2006–2010",
                "pl_xpath": "/article/body/sec[1]/p[1]/xref[5]",
                "context_xpath": "substring(string(/article/body/sec[1]/p[1]),1,309)",
                "containers_title": [
                    "Introduction and background"
                ]
            },
            {
                "n_rp": 7,
                "xref_id": "",
                "pl_string": "2006–2010",
                "pl_xpath": "/article/body/sec[1]/p[1]/xref[5]",
                "context_xpath": "substring(string(/article/body/sec[1]/p[1]),1,309)",
                "containers_title": [
                    "Introduction and background"
                ]
            },
            {
                "n_rp": 8,
                "xref_id": "",
                "pl_string": "2006–2010",
                "pl_xpath": "/article/body/sec[1]/p[1]/xref[5]",
                "context_xpath": "substring(string(/article/body/sec[1]/p[1]),1,309)",
                "containers_title": [
                    "Introduction and background"
                ]
            },
            {
                "n_rp": 9,
                "xref_id": "",
                "pl_string": "2006–2010",
                "pl_xpath": "/article/body/sec[1]/p[1]/xref[5]",
                "context_xpath": "substring(string(/article/body/sec[1]/p[1]),1,309)",
                "containers_title": [
                    "Introduction and background"
                ]
            }
        ],
        [
            {
                "n_rp": 10,
                "xref_id": "CIT0048",
                "rp_string": "2006",
                "rp_xpath": "/article/body/sec[1]/p[1]/xref[6]",
                "context_xpath": "substring(string(/article/body/sec[1]/p[1]),311,256)",
                "containers_title": [
                    "Introduction and background"
                ],
                "pl_string": "(Rembe,2006; ZNASP, 2006–2010)",
                "pl_xpath": "substring(string(/article/body/sec[1]/p[1]),535,30)"
            },
            {
                "n_rp": 12,
                "xref_id": "CIT0065",
                "rp_string": "2006–2010",
                "pl_string": "(Rembe, 2006; ZNASP,2006–2010)",
                "rp_xpath": "/article/body/sec[1]/p[1]/xref[7]",
                "pl_xpath": "substring(string(/article/body/sec[1]/p[1]),535,30)",
                "context_xpath": "substring(string(/article/body/sec[1]/p[1]),311,256)",
                "containers_title": [
                    "Introduction and background"
                ]
            }
        ],
        [
            {
                "n_rp": 12,
                "xref_id": "CIT0065",
                "rp_string": "2006–2010",
                "pl_string": "(Rembe, 2006; ZNASP,2006–2010)",
                "rp_xpath": "/article/body/sec[1]/p[1]/xref[7]",
                "pl_xpath": "substring(string(/article/body/sec[1]/p[1]),535,30)",
                "context_xpath": "substring(string(/article/body/sec[1]/p[1]),311,256)",
                "containers_title": [
                    "Introduction and background"
                ]
            },
            {
                "n_rp": 13,
                "xref_id": "",
                "pl_string": "2006–2010",
                "pl_xpath": "/article/body/sec[1]/p[1]/xref[7]",
                "context_xpath": "substring(string(/article/body/sec[1]/p[1]),311,256)",
                "containers_title": [
                    "Introduction and background"
                ]
            },
            {
                "n_rp": 14,
                "xref_id": "",
                "pl_string": "2006–2010",
                "pl_xpath": "/article/body/sec[1]/p[1]/xref[7]",
                "context_xpath": "substring(string(/article/body/sec[1]/p[1]),311,256)",
                "containers_title": [
                    "Introduction and background"
                ]
            },
            {
                "n_rp": 15,
                "xref_id": "",
                "pl_string": "2006–2010",
                "pl_xpath": "/article/body/sec[1]/p[1]/xref[7]",
                "context_xpath": "substring(string(/article/body/sec[1]/p[1]),311,256)",
                "containers_title": [
                    "Introduction and background"
                ]
            },
            {
                "n_rp": 16,
                "xref_id": "",
                "pl_string": "2006–2010",
                "pl_xpath": "/article/body/sec[1]/p[1]/xref[7]",
                "context_xpath": "substring(string(/article/body/sec[1]/p[1]),311,256)",
                "containers_title": [
                    "Introduction and background"
                ]
            }
        ],
        [
            {
                "n_rp": 17,
                "xref_id": "CIT0059",
                "rp_string": "2003",
                "rp_xpath": "/article/body/sec[1]/p[1]/xref[8]",
                "context_xpath": "substring(string(/article/body/sec[1]/p[1]),568,259)",
                "containers_title": [
                    "Introduction and background"
                ]
            }
        ],
        [
            {
                "n_rp": 23,
                "xref_id": "CIT0065",
                "rp_string": "2006–2010",
                "pl_string": "2006–2010",
                "rp_xpath": "/article/body/sec[1]/p[1]/xref[9]",
                "pl_xpath": "/article/body/sec[1]/p[1]/xref[9]",
                "context_xpath": "substring(string(/article/body/sec[1]/p[1]),932,172)",
                "containers_title": [
                    "Introduction and background"
                ]
            },
            {
                "n_rp": 19,
                "xref_id": "",
                "pl_string": "2006–2010",
                "pl_xpath": "/article/body/sec[1]/p[1]/xref[9]",
                "context_xpath": "substring(string(/article/body/sec[1]/p[1]),932,172)",
                "containers_title": [
                    "Introduction and background"
                ]
            },
            {
                "n_rp": 20,
                "xref_id": "",
                "pl_string": "2006–2010",
                "pl_xpath": "/article/body/sec[1]/p[1]/xref[9]",
                "context_xpath": "substring(string(/article/body/sec[1]/p[1]),932,172)",
                "containers_title": [
                    "Introduction and background"
                ]
            },
            {
                "n_rp": 21,
                "xref_id": "",
                "pl_string": "2006–2010",
                "pl_xpath": "/article/body/sec[1]/p[1]/xref[9]",
                "context_xpath": "substring(string(/article/body/sec[1]/p[1]),932,172)",
                "containers_title": [
                    "Introduction and background"
                ]
            },
            {
                "n_rp": 22,
                "xref_id": "",
                "pl_string": "2006–2010",
                "pl_xpath": "/article/body/sec[1]/p[1]/xref[9]",
                "context_xpath": "substring(string(/article/body/sec[1]/p[1]),932,172)",
                "containers_title": [
                    "Introduction and background"
                ]
            }
        ],
        [
            {
                "n_rp": 23,
                "xref_id": "CIT0065",
                "rp_string": "2006–2010",
                "pl_string": "2006–2010",
                "rp_xpath": "/article/body/sec[1]/p[1]/xref[9]",
                "pl_xpath": "/article/body/sec[1]/p[1]/xref[9]",
                "context_xpath": "substring(string(/article/body/sec[1]/p[1]),932,172)",
                "containers_title": [
                    "Introduction and background"
                ]
            }
        ],
        [
            {
                "n_rp": 29,
                "xref_id": "CIT0065",
                "rp_string": "2006–2010",
                "pl_string": "2006–2010",
                "rp_xpath": "/article/body/sec[1]/p[1]/xref[10]",
                "pl_xpath": "/article/body/sec[1]/p[1]/xref[10]",
                "context_xpath": "substring(string(/article/body/sec[1]/p[1]),1105,141)",
                "containers_title": [
                    "Introduction and background"
                ]
            },
            {
                "n_rp": 25,
                "xref_id": "",
                "pl_string": "2006–2010",
                "pl_xpath": "/article/body/sec[1]/p[1]/xref[10]",
                "context_xpath": "substring(string(/article/body/sec[1]/p[1]),1105,141)",
                "containers_title": [
                    "Introduction and background"
                ]
            },
            {
                "n_rp": 26,
                "xref_id": "",
                "pl_string": "2006–2010",
                "pl_xpath": "/article/body/sec[1]/p[1]/xref[10]",
                "context_xpath": "substring(string(/article/body/sec[1]/p[1]),1105,141)",
                "containers_title": [
                    "Introduction and background"
                ]
            },
            {
                "n_rp": 27,
                "xref_id": "",
                "pl_string": "2006–2010",
                "pl_xpath": "/article/body/sec[1]/p[1]/xref[10]",
                "context_xpath": "substring(string(/article/body/sec[1]/p[1]),1105,141)",
                "containers_title": [
                    "Introduction and background"
                ]
            },
            {
                "n_rp": 28,
                "xref_id": "",
                "pl_string": "2006–2010",
                "pl_xpath": "/article/body/sec[1]/p[1]/xref[10]",
                "context_xpath": "substring(string(/article/body/sec[1]/p[1]),1105,141)",
                "containers_title": [
                    "Introduction and background"
                ]
            }
        ],
        [
            {
                "n_rp": 29,
                "xref_id": "CIT0065",
                "rp_string": "2006–2010",
                "pl_string": "2006–2010",
                "rp_xpath": "/article/body/sec[1]/p[1]/xref[10]",
                "pl_xpath": "/article/body/sec[1]/p[1]/xref[10]",
                "context_xpath": "substring(string(/article/body/sec[1]/p[1]),1105,141)",
                "containers_title": [
                    "Introduction and background"
                ]
            }
        ],
        [
            {
                "n_rp": 30,
                "xref_id": "CIT0032",
                "rp_string": "2007",
                "rp_xpath": "/article/body/sec[1]/p[1]/xref[11]",
                "context_xpath": "substring(string(/article/body/sec[1]/p[1]),1247,258)",
                "containers_title": [
                    "Introduction and background"
                ]
            }
        ],
        [
            {
                "n_rp": 31,
                "xref_id": "CIT0015",
                "rp_string": "2013",
                "rp_xpath": "/article/body/sec[1]/p[1]/xref[12]",
                "context_xpath": "substring(string(/article/body/sec[1]/p[1]),1247,258)",
                "containers_title": [
                    "Introduction and background"
                ]
            }
        ],
        [
            {
                "n_rp": 32,
                "xref_id": "CIT0045",
                "rp_string": "2007",
                "rp_xpath": "/article/body/sec[1]/p[1]/xref[13]",
                "context_xpath": "substring(string(/article/body/sec[1]/p[1]),1506,258)",
                "containers_title": [
                    "Introduction and background"
                ]
            }
        ],
        [
            {
                "n_rp": 33,
                "xref_id": "CIT0042",
                "rp_string": "2009",
                "rp_xpath": "/article/body/sec[1]/p[2]/xref[1]",
                "context_xpath": "substring(string(/article/body/sec[1]/p[2]),1,246)",
                "containers_title": [
                    "Introduction and background"
                ]
            }
        ],
        [
            {
                "n_rp": 34,
                "xref_id": "CIT0002",
                "rp_string": "2013",
                "rp_xpath": "/article/body/sec[1]/p[2]/xref[2]",
                "context_xpath": "substring(string(/article/body/sec[1]/p[2]),248,162)",
                "containers_title": [
                    "Introduction and background"
                ],
                "pl_string": "(Batisai,2013; MSF Report, 2009)",
                "pl_xpath": "substring(string(/article/body/sec[1]/p[2]),376,32)"
            },
            {
                "n_rp": 35,
                "xref_id": "CIT0036",
                "rp_string": "2009",
                "rp_xpath": "/article/body/sec[1]/p[2]/xref[3]",
                "context_xpath": "substring(string(/article/body/sec[1]/p[2]),248,162)",
                "containers_title": [
                    "Introduction and background"
                ],
                "pl_string": "(Batisai, 2013; MSF Report,2009)",
                "pl_xpath": "substring(string(/article/body/sec[1]/p[2]),376,32)"
            }
        ],
        [
            {
                "n_rp": 36,
                "xref_id": "CIT0042",
                "rp_string": "2009",
                "rp_xpath": "/article/body/sec[1]/p[2]/xref[4]",
                "context_xpath": "substring(string(/article/body/sec[1]/p[2]),411,143)",
                "containers_title": [
                    "Introduction and background"
                ]
            }
        ],
        [
            {
                "n_rp": 37,
                "xref_id": "CIT0015",
                "rp_string": "2013",
                "rp_xpath": "/article/body/sec[1]/p[2]/xref[5]",
                "context_xpath": "substring(string(/article/body/sec[1]/p[2]),555,235)",
                "containers_title": [
                    "Introduction and background"
                ],
                "pl_string": "(Duri et al.,2013; Physicians for Human Rights, 2009)",
                "pl_xpath": "substring(string(/article/body/sec[1]/p[2]),735,53)"
            },
            {
                "n_rp": 38,
                "xref_id": "CIT0042",
                "rp_string": "2009",
                "rp_xpath": "/article/body/sec[1]/p[2]/xref[6]",
                "context_xpath": "substring(string(/article/body/sec[1]/p[2]),555,235)",
                "containers_title": [
                    "Introduction and background"
                ],
                "pl_string": "(Duri et al., 2013; Physicians for Human Rights,2009)",
                "pl_xpath": "substring(string(/article/body/sec[1]/p[2]),735,53)"
            }
        ],
        [
            {
                "n_rp": 39,
                "xref_id": "CIT0060",
                "rp_string": "2014",
                "rp_xpath": "/article/body/sec[1]/p[2]/xref[7]",
                "context_xpath": "substring(string(/article/body/sec[1]/p[2]),791,223)",
                "containers_title": [
                    "Introduction and background"
                ]
            }
        ],
        [
            {
                "n_rp": 40,
                "xref_id": "CIT0062",
                "rp_string": "2006",
                "rp_xpath": "/article/body/sec[1]/p[2]/xref[8]",
                "context_xpath": "substring(string(/article/body/sec[1]/p[2]),791,223)",
                "containers_title": [
                    "Introduction and background"
                ]
            }
        ],
        [
            {
                "n_rp": 41,
                "xref_id": "CIT0062",
                "rp_string": "2006",
                "rp_xpath": "/article/body/sec[1]/p[2]/xref[9]",
                "context_xpath": "substring(string(/article/body/sec[1]/p[2]),1015,135)",
                "containers_title": [
                    "Introduction and background"
                ]
            }
        ],
        [
            {
                "n_rp": 42,
                "xref_id": "CIT0002",
                "rp_string": "2013",
                "rp_xpath": "/article/body/sec[1]/p[2]/xref[10]",
                "context_xpath": "substring(string(/article/body/sec[1]/p[2]),1151,229)",
                "containers_title": [
                    "Introduction and background"
                ],
                "pl_string": "(Batisai,2013, 2016; Duri et al., 2013)",
                "pl_xpath": "substring(string(/article/body/sec[1]/p[2]),1339,39)"
            },
            {
                "n_rp": 43,
                "xref_id": "CIT0003",
                "rp_string": "2016",
                "rp_xpath": "/article/body/sec[1]/p[2]/xref[11]",
                "context_xpath": "substring(string(/article/body/sec[1]/p[2]),1151,229)",
                "containers_title": [
                    "Introduction and background"
                ],
                "pl_string": "(Batisai, 2013,2016; Duri et al., 2013)",
                "pl_xpath": "substring(string(/article/body/sec[1]/p[2]),1339,39)"
            },
            {
                "n_rp": 44,
                "xref_id": "CIT0015",
                "rp_string": "2013",
                "rp_xpath": "/article/body/sec[1]/p[2]/xref[12]",
                "context_xpath": "substring(string(/article/body/sec[1]/p[2]),1151,229)",
                "containers_title": [
                    "Introduction and background"
                ],
                "pl_string": "(Batisai, 2013, 2016; Duri et al.,2013)",
                "pl_xpath": "substring(string(/article/body/sec[1]/p[2]),1339,39)"
            }
        ],
        [
            {
                "n_rp": 45,
                "xref_id": "CIT0038",
                "rp_string": "1999",
                "rp_xpath": "/article/body/sec[1]/p[3]/xref[1]",
                "context_xpath": "substring(string(/article/body/sec[1]/p[3]),1,277)",
                "containers_title": [
                    "Introduction and background"
                ]
            }
        ],
        [
            {
                "n_rp": 46,
                "xref_id": "CIT0015",
                "rp_string": "2013",
                "rp_xpath": "/article/body/sec[1]/p[3]/xref[2]",
                "context_xpath": "substring(string(/article/body/sec[1]/p[3]),279,313)",
                "containers_title": [
                    "Introduction and background"
                ]
            }
        ],
        [
            {
                "n_rp": 47,
                "xref_id": "CIT0003",
                "rp_string": "2016",
                "rp_xpath": "/article/body/sec[1]/p[3]/xref[3]",
                "context_xpath": "substring(string(/article/body/sec[1]/p[3]),749,242)",
                "containers_title": [
                    "Introduction and background"
                ],
                "pl_string": "(Batisai,2016; Bene & Darkoh, 2014; Kautzky & Tollman, 2008; O’Brien & Broom, 2014)",
                "pl_xpath": "substring(string(/article/body/sec[1]/p[3]),906,83)"
            },
            {
                "n_rp": 48,
                "xref_id": "CIT0004",
                "rp_string": "2014",
                "rp_xpath": "/article/body/sec[1]/p[3]/xref[4]",
                "context_xpath": "substring(string(/article/body/sec[1]/p[3]),749,242)",
                "containers_title": [
                    "Introduction and background"
                ],
                "pl_string": "(Batisai, 2016; Bene & Darkoh,2014; Kautzky & Tollman, 2008; O’Brien & Broom, 2014)",
                "pl_xpath": "substring(string(/article/body/sec[1]/p[3]),906,83)"
            },
            {
                "n_rp": 49,
                "xref_id": "CIT0028",
                "rp_string": "2008",
                "rp_xpath": "/article/body/sec[1]/p[3]/xref[5]",
                "context_xpath": "substring(string(/article/body/sec[1]/p[3]),749,242)",
                "containers_title": [
                    "Introduction and background"
                ],
                "pl_string": "(Batisai, 2016; Bene & Darkoh, 2014; Kautzky & Tollman,2008; O’Brien & Broom, 2014)",
                "pl_xpath": "substring(string(/article/body/sec[1]/p[3]),906,83)"
            },
            {
                "n_rp": 50,
                "xref_id": "CIT0041",
                "rp_string": "2014",
                "rp_xpath": "/article/body/sec[1]/p[3]/xref[6]",
                "context_xpath": "substring(string(/article/body/sec[1]/p[3]),749,242)",
                "containers_title": [
                    "Introduction and background"
                ],
                "pl_string": "(Batisai, 2016; Bene & Darkoh, 2014; Kautzky & Tollman, 2008; O’Brien & Broom,2014)",
                "pl_xpath": "substring(string(/article/body/sec[1]/p[3]),906,83)"
            }
        ],
        [
            {
                "n_rp": 51,
                "xref_id": "CIT0029",
                "rp_string": "2017",
                "rp_xpath": "/article/body/sec[1]/p[4]/xref[1]",
                "context_xpath": "substring(string(/article/body/sec[1]/p[4]),167,276)",
                "containers_title": [
                    "Introduction and background"
                ],
                "pl_string": "(Leff,2017; Munshi & Bezuidenhout, 2017; NAC, 2010; Naylor & Keating, 2008)",
                "pl_xpath": "substring(string(/article/body/sec[1]/p[4]),366,75)"
            },
            {
                "n_rp": 52,
                "xref_id": "CIT0037",
                "rp_string": "2017",
                "rp_xpath": "/article/body/sec[1]/p[4]/xref[2]",
                "context_xpath": "substring(string(/article/body/sec[1]/p[4]),167,276)",
                "containers_title": [
                    "Introduction and background"
                ],
                "pl_string": "(Leff, 2017; Munshi & Bezuidenhout,2017; NAC, 2010; Naylor & Keating, 2008)",
                "pl_xpath": "substring(string(/article/body/sec[1]/p[4]),366,75)"
            },
            {
                "n_rp": 53,
                "xref_id": "CIT0040",
                "rp_string": "2008",
                "rp_xpath": "/article/body/sec[1]/p[4]/xref[3]",
                "context_xpath": "substring(string(/article/body/sec[1]/p[4]),167,276)",
                "containers_title": [
                    "Introduction and background"
                ],
                "pl_string": "(Leff, 2017; Munshi & Bezuidenhout, 2017; NAC, 2010; Naylor & Keating,2008)",
                "pl_xpath": "substring(string(/article/body/sec[1]/p[4]),366,75)"
            }
        ],
        [
            {
                "n_rp": 54,
                "xref_id": "CIT0014",
                "rp_string": "2005",
                "rp_xpath": "/article/body/sec[1]/sec[1]/p/xref[1]",
                "context_xpath": "substring(string(/article/body/sec[1]/sec[1]/p),221,148)",
                "containers_title": [
                    "Introduction and background",
                    "Origins and establishment of Ruvheneko Programme"
                ],
                "pl_string": "(Duffy,2005; Duri et al., 2013; World Health Organisation [WHO], 2005)",
                "pl_xpath": "substring(string(/article/body/sec[1]/sec[1]/p),275,70)"
            },
            {
                "n_rp": 55,
                "xref_id": "CIT0015",
                "rp_string": "2013",
                "rp_xpath": "/article/body/sec[1]/sec[1]/p/xref[2]",
                "context_xpath": "substring(string(/article/body/sec[1]/sec[1]/p),221,148)",
                "containers_title": [
                    "Introduction and background",
                    "Origins and establishment of Ruvheneko Programme"
                ],
                "pl_string": "(Duffy, 2005; Duri et al.,2013; World Health Organisation [WHO], 2005)",
                "pl_xpath": "substring(string(/article/body/sec[1]/sec[1]/p),275,70)"
            },
            {
                "n_rp": 56,
                "xref_id": "CIT0061",
                "rp_string": "2005",
                "rp_xpath": "/article/body/sec[1]/sec[1]/p/xref[3]",
                "context_xpath": "substring(string(/article/body/sec[1]/sec[1]/p),221,148)",
                "containers_title": [
                    "Introduction and background",
                    "Origins and establishment of Ruvheneko Programme"
                ],
                "pl_string": "(Duffy, 2005; Duri et al., 2013; World Health Organisation [WHO],2005)",
                "pl_xpath": "substring(string(/article/body/sec[1]/sec[1]/p),275,70)"
            }
        ],
        [
            {
                "n_rp": 57,
                "xref_id": "CIT0026",
                "rp_string": "2001",
                "rp_xpath": "/article/body/sec[1]/sec[1]/p/xref[4]",
                "context_xpath": "substring(string(/article/body/sec[1]/sec[1]/p),1979,206)",
                "containers_title": [
                    "Introduction and background",
                    "Origins and establishment of Ruvheneko Programme"
                ]
            }
        ],
        [
            {
                "n_rp": 58,
                "xref_id": "CIT0005",
                "rp_string": "2009",
                "rp_xpath": "/article/body/sec[1]/sec[2]/p[1]/xref[1]",
                "context_xpath": "substring(string(/article/body/sec[1]/sec[2]/p[1]),175,207)",
                "containers_title": [
                    "Introduction and background",
                    "Situating Ruvheneko Programme within the confines of social capital theory"
                ]
            }
        ],
        [
            {
                "n_rp": 59,
                "xref_id": "CIT0016",
                "rp_string": "2000",
                "rp_xpath": "/article/body/sec[1]/sec[2]/p[1]/xref[2]",
                "context_xpath": "substring(string(/article/body/sec[1]/sec[2]/p[1]),383,166)",
                "containers_title": [
                    "Introduction and background",
                    "Situating Ruvheneko Programme within the confines of social capital theory"
                ]
            }
        ],
        [
            {
                "n_rp": 60,
                "xref_id": "CIT0046",
                "rp_string": "1993",
                "rp_xpath": "/article/body/sec[1]/sec[2]/p[1]/xref[3]",
                "context_xpath": "substring(string(/article/body/sec[1]/sec[2]/p[1]),550,428)",
                "containers_title": [
                    "Introduction and background",
                    "Situating Ruvheneko Programme within the confines of social capital theory"
                ],
                "pl_string": "(1993, p. 167)",
                "pl_xpath": "substring(string(/article/body/sec[1]/sec[2]/p[1]),608,14)"
            },
            {
                "n_rp": 61,
                "xref_id": "CIT0005",
                "rp_string": "2009",
                "rp_xpath": "/article/body/sec[1]/sec[2]/p[1]/xref[4]",
                "context_xpath": "substring(string(/article/body/sec[1]/sec[2]/p[1]),550,428)",
                "containers_title": [
                    "Introduction and background",
                    "Situating Ruvheneko Programme within the confines of social capital theory"
                ],
                "pl_string": "(Bhandari & Yasunobu,2009; Putnam, 1993)",
                "pl_xpath": "substring(string(/article/body/sec[1]/sec[2]/p[1]),936,40)"
            },
            {
                "n_rp": 62,
                "xref_id": "CIT0046",
                "rp_string": "1993",
                "rp_xpath": "/article/body/sec[1]/sec[2]/p[1]/xref[5]",
                "context_xpath": "substring(string(/article/body/sec[1]/sec[2]/p[1]),550,428)",
                "containers_title": [
                    "Introduction and background",
                    "Situating Ruvheneko Programme within the confines of social capital theory"
                ],
                "pl_string": "(Bhandari & Yasunobu, 2009; Putnam,1993)",
                "pl_xpath": "substring(string(/article/body/sec[1]/sec[2]/p[1]),936,40)"
            }
        ],
        [
            {
                "n_rp": 63,
                "xref_id": "CIT0005",
                "rp_string": "2009",
                "rp_xpath": "/article/body/sec[1]/sec[2]/p[1]/xref[6]",
                "context_xpath": "substring(string(/article/body/sec[1]/sec[2]/p[1]),979,182)",
                "containers_title": [
                    "Introduction and background",
                    "Situating Ruvheneko Programme within the confines of social capital theory"
                ],
                "pl_string": "(Bhandari & Yasunobu,2009; Coleman, 1990)",
                "pl_xpath": "substring(string(/article/body/sec[1]/sec[2]/p[1]),1118,41)"
            },
            {
                "n_rp": 64,
                "xref_id": "CIT0012",
                "rp_string": "1990",
                "rp_xpath": "/article/body/sec[1]/sec[2]/p[1]/xref[7]",
                "context_xpath": "substring(string(/article/body/sec[1]/sec[2]/p[1]),979,182)",
                "containers_title": [
                    "Introduction and background",
                    "Situating Ruvheneko Programme within the confines of social capital theory"
                ],
                "pl_string": "(Bhandari & Yasunobu, 2009; Coleman,1990)",
                "pl_xpath": "substring(string(/article/body/sec[1]/sec[2]/p[1]),1118,41)"
            }
        ],
        [
            {
                "n_rp": 65,
                "xref_id": "CIT0022",
                "rp_string": "2000",
                "rp_xpath": "/article/body/sec[1]/sec[2]/p[1]/xref[8]",
                "context_xpath": "substring(string(/article/body/sec[1]/sec[2]/p[1]),1162,234)",
                "containers_title": [
                    "Introduction and background",
                    "Situating Ruvheneko Programme within the confines of social capital theory"
                ]
            }
        ],
        [
            {
                "n_rp": 66,
                "xref_id": "CIT0047",
                "rp_string": "1995",
                "rp_xpath": "/article/body/sec[1]/sec[2]/p[2]/xref[1]",
                "context_xpath": "substring(string(/article/body/sec[1]/sec[2]/p[2]),493,304)",
                "containers_title": [
                    "Introduction and background",
                    "Situating Ruvheneko Programme within the confines of social capital theory"
                ]
            }
        ],
        [
            {
                "n_rp": 67,
                "xref_id": "CIT0017",
                "rp_string": "1996",
                "rp_xpath": "/article/body/sec[1]/sec[2]/p[2]/xref[2]",
                "context_xpath": "substring(string(/article/body/sec[1]/sec[2]/p[2]),798,154)",
                "containers_title": [
                    "Introduction and background",
                    "Situating Ruvheneko Programme within the confines of social capital theory"
                ]
            }
        ],
        [
            {
                "n_rp": 68,
                "xref_id": "CIT0021",
                "rp_string": "2008",
                "rp_xpath": "/article/body/sec[1]/sec[2]/p[3]/xref[1]",
                "context_xpath": "substring(string(/article/body/sec[1]/sec[2]/p[3]),1,169)",
                "containers_title": [
                    "Introduction and background",
                    "Situating Ruvheneko Programme within the confines of social capital theory"
                ]
            }
        ],
        [
            {
                "n_rp": 69,
                "xref_id": "CIT0039",
                "rp_string": "2002",
                "rp_xpath": "/article/body/sec[1]/sec[2]/p[3]/xref[2]",
                "context_xpath": "substring(string(/article/body/sec[1]/sec[2]/p[3]),1,169)",
                "containers_title": [
                    "Introduction and background",
                    "Situating Ruvheneko Programme within the confines of social capital theory"
                ]
            }
        ],
        [
            {
                "n_rp": 70,
                "xref_id": "CIT0019",
                "rp_string": "2001",
                "rp_xpath": "/article/body/sec[1]/sec[2]/p[3]/xref[3]",
                "context_xpath": "substring(string(/article/body/sec[1]/sec[2]/p[3]),1,169)",
                "containers_title": [
                    "Introduction and background",
                    "Situating Ruvheneko Programme within the confines of social capital theory"
                ]
            }
        ],
        [
            {
                "n_rp": 71,
                "xref_id": "CIT0035",
                "rp_string": "2006",
                "rp_xpath": "/article/body/sec[1]/sec[2]/p[3]/xref[4]",
                "context_xpath": "substring(string(/article/body/sec[1]/sec[2]/p[3]),1,169)",
                "containers_title": [
                    "Introduction and background",
                    "Situating Ruvheneko Programme within the confines of social capital theory"
                ]
            }
        ],
        [
            {
                "n_rp": 72,
                "xref_id": "CIT0057",
                "rp_string": "2003",
                "rp_xpath": "/article/body/sec[2]/p/xref",
                "context_xpath": "substring(string(/article/body/sec[2]/p),275,369)",
                "containers_title": [
                    "Aim of the study"
                ]
            }
        ],
        [
            {
                "n_rp": 73,
                "xref_id": "CIT0001",
                "rp_string": "2007",
                "rp_xpath": "/article/body/sec[3]/p[1]/xref[1]",
                "context_xpath": "substring(string(/article/body/sec[3]/p[1]),244,201)",
                "containers_title": [
                    "Methodology"
                ],
                "pl_string": "(Babbie,2007; Hennink, Hutter, & Bailey, 2011)",
                "pl_xpath": "substring(string(/article/body/sec[3]/p[1]),397,46)"
            },
            {
                "n_rp": 74,
                "xref_id": "CIT0025",
                "rp_string": "2011",
                "rp_xpath": "/article/body/sec[3]/p[1]/xref[2]",
                "context_xpath": "substring(string(/article/body/sec[3]/p[1]),244,201)",
                "containers_title": [
                    "Methodology"
                ],
                "pl_string": "(Babbie, 2007; Hennink, Hutter, & Bailey,2011)",
                "pl_xpath": "substring(string(/article/body/sec[3]/p[1]),397,46)"
            }
        ],
        [
            {
                "n_rp": 75,
                "xref_id": "CIT0043",
                "rp_string": "2008",
                "rp_xpath": "/article/body/sec[3]/p[1]/xref[3]",
                "context_xpath": "substring(string(/article/body/sec[3]/p[1]),446,131)",
                "containers_title": [
                    "Methodology"
                ]
            }
        ],
        [
            {
                "n_rp": 76,
                "xref_id": "CIT0063",
                "rp_string": "2003",
                "rp_xpath": "/article/body/sec[3]/p[1]/xref[4]",
                "context_xpath": "substring(string(/article/body/sec[3]/p[1]),578,222)",
                "containers_title": [
                    "Methodology"
                ]
            }
        ],
        [
            {
                "n_rp": 77,
                "xref_id": "CIT0044",
                "rp_string": "1998",
                "rp_xpath": "/article/body/sec[3]/p[2]/xref",
                "context_xpath": "substring(string(/article/body/sec[3]/p[2]),1,204)",
                "containers_title": [
                    "Methodology"
                ]
            }
        ],
        [
            {
                "n_rp": 78,
                "xref_id": "CIT0034",
                "rp_string": "2006",
                "rp_xpath": "/article/body/sec[3]/sec[2]/p[1]/xref[1]",
                "context_xpath": "substring(string(/article/body/sec[3]/sec[2]/p[1]),1,166)",
                "containers_title": [
                    "Methodology",
                    "Data gathering approach"
                ]
            }
        ],
        [
            {
                "n_rp": 79,
                "xref_id": "CIT0013",
                "rp_string": "2007",
                "rp_xpath": "/article/body/sec[3]/sec[2]/p[1]/xref[2]",
                "context_xpath": "substring(string(/article/body/sec[3]/sec[2]/p[1]),372,206)",
                "containers_title": [
                    "Methodology",
                    "Data gathering approach"
                ]
            }
        ],
        [
            {
                "n_rp": 80,
                "xref_id": "CIT0052",
                "rp_string": "2004",
                "rp_xpath": "/article/body/sec[3]/sec[2]/p[1]/xref[3]",
                "context_xpath": "substring(string(/article/body/sec[3]/sec[2]/p[1]),372,206)",
                "containers_title": [
                    "Methodology",
                    "Data gathering approach"
                ]
            }
        ],
        [
            {
                "n_rp": 81,
                "xref_id": "CIT0001",
                "rp_string": "2007",
                "rp_xpath": "/article/body/sec[3]/sec[2]/p[2]/xref",
                "context_xpath": "substring(string(/article/body/sec[3]/sec[2]/p[2]),391,239)",
                "containers_title": [
                    "Methodology",
                    "Data gathering approach"
                ]
            }
        ],
        [
            {
                "n_rp": 82,
                "xref_id": "CIT0064",
                "rp_string": "2013",
                "rp_xpath": "/article/body/sec[3]/sec[2]/p[3]/xref",
                "context_xpath": "substring(string(/article/body/sec[3]/sec[2]/p[3]),159,329)",
                "containers_title": [
                    "Methodology",
                    "Data gathering approach"
                ]
            }
        ],
        [
            {
                "n_rp": 90,
                "xref_id": "CIT0050",
                "rp_string": "2003–2009",
                "pl_string": "2003–2009",
                "rp_xpath": "/article/body/sec[3]/sec[2]/p[4]/xref[1]",
                "pl_xpath": "/article/body/sec[3]/sec[2]/p[4]/xref[1]",
                "context_xpath": "substring(string(/article/body/sec[3]/sec[2]/p[4]),1,312)",
                "containers_title": [
                    "Methodology",
                    "Data gathering approach"
                ]
            },
            {
                "n_rp": 84,
                "xref_id": "",
                "pl_string": "2003–2009",
                "pl_xpath": "/article/body/sec[3]/sec[2]/p[4]/xref[1]",
                "context_xpath": "substring(string(/article/body/sec[3]/sec[2]/p[4]),1,312)",
                "containers_title": [
                    "Methodology",
                    "Data gathering approach"
                ]
            },
            {
                "n_rp": 85,
                "xref_id": "",
                "pl_string": "2003–2009",
                "pl_xpath": "/article/body/sec[3]/sec[2]/p[4]/xref[1]",
                "context_xpath": "substring(string(/article/body/sec[3]/sec[2]/p[4]),1,312)",
                "containers_title": [
                    "Methodology",
                    "Data gathering approach"
                ]
            },
            {
                "n_rp": 86,
                "xref_id": "",
                "pl_string": "2003–2009",
                "pl_xpath": "/article/body/sec[3]/sec[2]/p[4]/xref[1]",
                "context_xpath": "substring(string(/article/body/sec[3]/sec[2]/p[4]),1,312)",
                "containers_title": [
                    "Methodology",
                    "Data gathering approach"
                ]
            },
            {
                "n_rp": 87,
                "xref_id": "",
                "pl_string": "2003–2009",
                "pl_xpath": "/article/body/sec[3]/sec[2]/p[4]/xref[1]",
                "context_xpath": "substring(string(/article/body/sec[3]/sec[2]/p[4]),1,312)",
                "containers_title": [
                    "Methodology",
                    "Data gathering approach"
                ]
            },
            {
                "n_rp": 88,
                "xref_id": "",
                "pl_string": "2003–2009",
                "pl_xpath": "/article/body/sec[3]/sec[2]/p[4]/xref[1]",
                "context_xpath": "substring(string(/article/body/sec[3]/sec[2]/p[4]),1,312)",
                "containers_title": [
                    "Methodology",
                    "Data gathering approach"
                ]
            },
            {
                "n_rp": 89,
                "xref_id": "",
                "pl_string": "2003–2009",
                "pl_xpath": "/article/body/sec[3]/sec[2]/p[4]/xref[1]",
                "context_xpath": "substring(string(/article/body/sec[3]/sec[2]/p[4]),1,312)",
                "containers_title": [
                    "Methodology",
                    "Data gathering approach"
                ]
            }
        ],
        [
            {
                "n_rp": 90,
                "xref_id": "CIT0050",
                "rp_string": "2003–2009",
                "pl_string": "2003–2009",
                "rp_xpath": "/article/body/sec[3]/sec[2]/p[4]/xref[1]",
                "pl_xpath": "/article/body/sec[3]/sec[2]/p[4]/xref[1]",
                "context_xpath": "substring(string(/article/body/sec[3]/sec[2]/p[4]),1,312)",
                "containers_title": [
                    "Methodology",
                    "Data gathering approach"
                ]
            }
        ],
        [
            {
                "n_rp": 91,
                "xref_id": "CIT0053",
                "rp_string": "1999",
                "rp_xpath": "/article/body/sec[3]/sec[2]/p[4]/xref[2]",
                "context_xpath": "substring(string(/article/body/sec[3]/sec[2]/p[4]),314,128)",
                "containers_title": [
                    "Methodology",
                    "Data gathering approach"
                ],
                "pl_string": "Apart from the collection of primary data, the study also benefitted from copious amount of secondary data sources in the form of official reports of the Ruvheneko Programme namely End of Phase 1 Report: May 2003–March 2006 and Ruvheneko Programme Report on Key Programme Achievements for the period (2003–2009). Reviewed also were St Theresa’s Hospital Annual Reports of 1999, 2001, 2009 as well as the St. Theresa’s Hospital PMTCT of 2009. Lastly, related literature on HIV and AIDS trends in Zimbabwe as well as official UNAIDS reports formed part of secondary data sources.",
                "pl_xpath": "/article/body/sec[3]/sec[2]/p[4]"
            },
            {
                "n_rp": 92,
                "xref_id": "CIT0054",
                "rp_string": "2001",
                "rp_xpath": "/article/body/sec[3]/sec[2]/p[4]/xref[3]",
                "context_xpath": "substring(string(/article/body/sec[3]/sec[2]/p[4]),314,128)",
                "containers_title": [
                    "Methodology",
                    "Data gathering approach"
                ],
                "pl_string": "Apart from the collection of primary data, the study also benefitted from copious amount of secondary data sources in the form of official reports of the Ruvheneko Programme namely End of Phase 1 Report: May 2003–March 2006 and Ruvheneko Programme Report on Key Programme Achievements for the period (2003–2009). Reviewed also were St Theresa’s Hospital Annual Reports of 1999, 2001, 2009 as well as the St. Theresa’s Hospital PMTCT of 2009. Lastly, related literature on HIV and AIDS trends in Zimbabwe as well as official UNAIDS reports formed part of secondary data sources.",
                "pl_xpath": "/article/body/sec[3]/sec[2]/p[4]"
            },
            {
                "n_rp": 93,
                "xref_id": "CIT0055",
                "rp_string": "2009",
                "rp_xpath": "/article/body/sec[3]/sec[2]/p[4]/xref[4]",
                "context_xpath": "substring(string(/article/body/sec[3]/sec[2]/p[4]),314,128)",
                "containers_title": [
                    "Methodology",
                    "Data gathering approach"
                ],
                "pl_string": "Apart from the collection of primary data, the study also benefitted from copious amount of secondary data sources in the form of official reports of the Ruvheneko Programme namely End of Phase 1 Report: May 2003–March 2006 and Ruvheneko Programme Report on Key Programme Achievements for the period (2003–2009). Reviewed also were St Theresa’s Hospital Annual Reports of 1999, 2001, 2009 as well as the St. Theresa’s Hospital PMTCT of 2009. Lastly, related literature on HIV and AIDS trends in Zimbabwe as well as official UNAIDS reports formed part of secondary data sources.",
                "pl_xpath": "/article/body/sec[3]/sec[2]/p[4]"
            }
        ],
        [
            {
                "n_rp": 94,
                "xref_id": "CIT0058",
                "rp_string": "2008",
                "rp_xpath": "/article/body/sec[3]/sec[3]/p/xref[1]",
                "context_xpath": "substring(string(/article/body/sec[3]/sec[3]/p),178,99)",
                "containers_title": [
                    "Methodology",
                    "Data analysis"
                ]
            }
        ],
        [
            {
                "n_rp": 95,
                "xref_id": "CIT0006",
                "rp_string": "2006",
                "rp_xpath": "/article/body/sec[3]/sec[3]/p/xref[2]",
                "context_xpath": "substring(string(/article/body/sec[3]/sec[3]/p),357,241)",
                "containers_title": [
                    "Methodology",
                    "Data analysis"
                ]
            }
        ],
        [
            {
                "n_rp": 96,
                "xref_id": "CIT0023",
                "rp_string": "1997",
                "rp_xpath": "/article/body/sec[3]/sec[3]/p/xref[3]",
                "context_xpath": "substring(string(/article/body/sec[3]/sec[3]/p),357,241)",
                "containers_title": [
                    "Methodology",
                    "Data analysis"
                ]
            }
        ],
        [
            {
                "n_rp": 97,
                "xref_id": "CIT0054",
                "rp_string": "2001",
                "rp_xpath": "/article/body/sec[4]/sec[1]/p[2]/xref",
                "context_xpath": "substring(string(/article/body/sec[4]/sec[1]/p[2]),1,332)",
                "containers_title": [
                    "Findings",
                    "Chirumhanzu home based-care project"
                ]
            }
        ],
        [
            {
                "n_rp": 98,
                "xref_id": "CIT0018",
                "rp_string": "2012",
                "rp_xpath": "/article/body/sec[4]/sec[6]/p/xref",
                "context_xpath": "substring(string(/article/body/sec[4]/sec[6]/p),951,223)",
                "containers_title": [
                    "Findings",
                    "A gendered approach to the fight against HIV and AIDS"
                ]
            }
        ],
        [
            {
                "n_rp": 99,
                "xref_id": "CIT0009",
                "rp_string": "2003",
                "rp_xpath": "/article/body/sec[5]/p[1]/xref",
                "context_xpath": "substring(string(/article/body/sec[5]/p[1]),1,369)",
                "containers_title": [
                    "Discussion of findings"
                ]
            }
        ],
        [
            {
                "n_rp": 100,
                "xref_id": "CIT0049",
                "rp_string": "2013",
                "rp_xpath": "/article/body/sec[5]/p[2]/xref[1]",
                "context_xpath": "substring(string(/article/body/sec[5]/p[2]),255,172)",
                "containers_title": [
                    "Discussion of findings"
                ]
            }
        ],
        [
            {
                "n_rp": 101,
                "xref_id": "CIT0049",
                "rp_string": "2013",
                "rp_xpath": "/article/body/sec[5]/p[2]/xref[2]",
                "context_xpath": "substring(string(/article/body/sec[5]/p[2]),428,206)",
                "containers_title": [
                    "Discussion of findings"
                ]
            }
        ],
        [
            {
                "n_rp": 102,
                "xref_id": "CIT0051",
                "rp_string": "2006",
                "rp_xpath": "/article/body/sec[5]/p[2]/xref[3]",
                "context_xpath": "substring(string(/article/body/sec[5]/p[2]),635,175)",
                "containers_title": [
                    "Discussion of findings"
                ]
            }
        ],
        [
            {
                "n_rp": 103,
                "xref_id": "CIT0011",
                "rp_string": "2004",
                "rp_xpath": "/article/body/sec[5]/p[3]/xref",
                "context_xpath": "substring(string(/article/body/sec[5]/p[3]),113,190)",
                "containers_title": [
                    "Discussion of findings"
                ]
            }
        ],
        [
            {
                "n_rp": 104,
                "xref_id": "CIT0024",
                "rp_string": "2003",
                "rp_xpath": "/article/body/sec[5]/p[4]/xref[1]",
                "context_xpath": "substring(string(/article/body/sec[5]/p[4]),131,303)",
                "containers_title": [
                    "Discussion of findings"
                ]
            }
        ],
        [
            {
                "n_rp": 105,
                "xref_id": "CIT0008",
                "rp_string": "2009",
                "rp_xpath": "/article/body/sec[5]/p[4]/xref[2]",
                "context_xpath": "substring(string(/article/body/sec[5]/p[4]),554,323)",
                "containers_title": [
                    "Discussion of findings"
                ]
            }
        ],
        [
            {
                "n_rp": 106,
                "xref_id": "CIT0027",
                "rp_string": "2007",
                "rp_xpath": "/article/body/sec[5]/p[5]/xref[1]",
                "context_xpath": "substring(string(/article/body/sec[5]/p[5]),279,138)",
                "containers_title": [
                    "Discussion of findings"
                ]
            }
        ],
        [
            {
                "n_rp": 107,
                "xref_id": "CIT0033",
                "rp_string": "1969",
                "rp_xpath": "/article/body/sec[5]/p[5]/xref[2]",
                "context_xpath": "substring(string(/article/body/sec[5]/p[5]),418,141)",
                "containers_title": [
                    "Discussion of findings"
                ]
            }
        ],
        [
            {
                "n_rp": 108,
                "xref_id": "CIT0027",
                "rp_string": "2007",
                "rp_xpath": "/article/body/sec[5]/p[5]/xref[3]",
                "context_xpath": "substring(string(/article/body/sec[5]/p[5]),560,190)",
                "containers_title": [
                    "Discussion of findings"
                ]
            }
        ],
        [
            {
                "n_rp": 109,
                "xref_id": "CIT0010",
                "rp_string": "1994",
                "rp_xpath": "/article/body/sec[5]/p[6]/xref[1]",
                "context_xpath": "substring(string(/article/body/sec[5]/p[6]),1,302)",
                "containers_title": [
                    "Discussion of findings"
                ],
                "pl_string": "(Chambers,1994; Emmett, 2000; Swanepoel & De Beer, 2006)",
                "pl_xpath": "substring(string(/article/body/sec[5]/p[6]),245,56)"
            },
            {
                "n_rp": 110,
                "xref_id": "CIT0016",
                "rp_string": "2000",
                "rp_xpath": "/article/body/sec[5]/p[6]/xref[2]",
                "context_xpath": "substring(string(/article/body/sec[5]/p[6]),1,302)",
                "containers_title": [
                    "Discussion of findings"
                ],
                "pl_string": "(Chambers, 1994; Emmett,2000; Swanepoel & De Beer, 2006)",
                "pl_xpath": "substring(string(/article/body/sec[5]/p[6]),245,56)"
            },
            {
                "n_rp": 111,
                "xref_id": "CIT0056",
                "rp_string": "2006",
                "rp_xpath": "/article/body/sec[5]/p[6]/xref[3]",
                "context_xpath": "substring(string(/article/body/sec[5]/p[6]),1,302)",
                "containers_title": [
                    "Discussion of findings"
                ],
                "pl_string": "(Chambers, 1994; Emmett, 2000; Swanepoel & De Beer,2006)",
                "pl_xpath": "substring(string(/article/body/sec[5]/p[6]),245,56)"
            }
        ],
        [
            {
                "n_rp": 112,
                "xref_id": "CIT0010",
                "rp_string": "1994",
                "rp_xpath": "/article/body/sec[5]/p[6]/xref[4]",
                "context_xpath": "substring(string(/article/body/sec[5]/p[6]),304,159)",
                "containers_title": [
                    "Discussion of findings"
                ]
            }
        ],
        [
            {
                "n_rp": 113,
                "xref_id": "CIT0030",
                "rp_string": "2007",
                "rp_xpath": "/article/body/sec[5]/p[7]/xref",
                "context_xpath": "substring(string(/article/body/sec[5]/p[7]),1150,299)",
                "containers_title": [
                    "Discussion of findings"
                ]
            }
        ],
        [
            {
                "n_rp": 114,
                "xref_id": "CIT0020",
                "rp_string": "2005",
                "rp_xpath": "/article/body/sec[5]/p[8]/xref",
                "context_xpath": "substring(string(/article/body/sec[5]/p[8]),1,320)",
                "containers_title": [
                    "Discussion of findings"
                ]
            }
        ]
    ]
}